{
  "name": "funding-digest-financial-services",
  "version": "0.1.0",
  "category": "finance",
  "description": "Generate a polished one-page PowerPoint slide summarizing key takeaways from recent funding rounds and notable capital markets activity across a user's watched sectors or companies.",
  "intent_triggers": [
    "use the funding digest agent skill",
    "run a workflow for funding digest",
    "help me with funding digest",
    "我需要處理 funding digest 相關工作",
    "幫我啟用 funding digest 這個 skill",
    "用 agent skill 完成 funding digest",
    "use funding digest from financial-services"
  ],
  "input_schema": {
    "task": {
      "type": "string",
      "required": true,
      "description": "Natural-language task or instruction for the agent skill."
    },
    "context_path": {
      "type": "string",
      "required": false,
      "description": "Optional workspace path or file context for the skill."
    }
  },
  "output_schema": {
    "format": "text",
    "fields": [
      "result",
      "notes"
    ]
  },
  "examples": [
    {
      "intent": "Use the funding digest skill for this task.",
      "invocation": "codex --skill funding-digest \"<task>\""
    }
  ],
  "error_codes": {
    "1": "Skill invocation failed or required context was missing."
  },
  "tags": [
    "agent-skill",
    "apache-2.0",
    "finance",
    "mcpservers"
  ]
}
