{
  "name": "autoresearch",
  "version": "0.1.0",
  "category": "devops",
  "description": "Autonomous iterative experimentation loop for any programming task.",
  "intent_triggers": [
    "use the autoresearch agent skill",
    "run a workflow for autoresearch",
    "help me with autoresearch",
    "我需要處理 autoresearch 相關工作",
    "幫我啟用 autoresearch 這個 skill",
    "用 agent skill 完成 autoresearch",
    "use autoresearch from awesome-copilot"
  ],
  "input_schema": {
    "task": {
      "type": "string",
      "required": true,
      "description": "Natural-language task or instruction for the agent skill."
    },
    "context_path": {
      "type": "string",
      "required": false,
      "description": "Optional workspace path or file context for the skill."
    }
  },
  "output_schema": {
    "format": "text",
    "fields": [
      "result",
      "notes"
    ]
  },
  "examples": [
    {
      "intent": "Use the autoresearch skill for this task.",
      "invocation": "codex --skill autoresearch \"<task>\""
    }
  ],
  "error_codes": {
    "1": "Skill invocation failed or required context was missing."
  },
  "tags": [
    "agent-skill",
    "devops",
    "mcpservers",
    "mit"
  ]
}
