{
  "name": "grill-me",
  "version": "0.1.0",
  "category": "devops",
  "description": "Interview the user relentlessly about a plan or design until reaching shared understanding, resolving each branch of the decision tree.",
  "intent_triggers": [
    "use the grill me agent skill",
    "run a workflow for grill me",
    "help me with grill me",
    "我需要處理 grill me 相關工作",
    "幫我啟用 grill me 這個 skill",
    "用 agent skill 完成 grill me",
    "use grill me from sanity"
  ],
  "input_schema": {
    "task": {
      "type": "string",
      "required": true,
      "description": "Natural-language task or instruction for the agent skill."
    },
    "context_path": {
      "type": "string",
      "required": false,
      "description": "Optional workspace path or file context for the skill."
    }
  },
  "output_schema": {
    "format": "text",
    "fields": [
      "result",
      "notes"
    ]
  },
  "examples": [
    {
      "intent": "Use the grill me skill for this task.",
      "invocation": "codex --skill grill-me \"<task>\""
    }
  ],
  "error_codes": {
    "1": "Skill invocation failed or required context was missing."
  },
  "tags": [
    "agent-skill",
    "devops",
    "mcpservers",
    "mit"
  ]
}
