{
  "name": "mapbox-cartography",
  "version": "0.1.0",
  "category": "devops",
  "description": "Expert guidance on map design principles, color theory, visual hierarchy, typography, and cartographic best practices for creating effective and beautiful maps with Mapbox.",
  "intent_triggers": [
    "use the mapbox cartography agent skill",
    "run a workflow for mapbox cartography",
    "help me with mapbox cartography",
    "我需要處理 mapbox cartography 相關工作",
    "幫我啟用 mapbox cartography 這個 skill",
    "用 agent skill 完成 mapbox cartography",
    "use mapbox cartography from mapbox-agent-skills"
  ],
  "input_schema": {
    "task": {
      "type": "string",
      "required": true,
      "description": "Natural-language task or instruction for the agent skill."
    },
    "context_path": {
      "type": "string",
      "required": false,
      "description": "Optional workspace path or file context for the skill."
    }
  },
  "output_schema": {
    "format": "text",
    "fields": [
      "result",
      "notes"
    ]
  },
  "examples": [
    {
      "intent": "Use the mapbox cartography skill for this task.",
      "invocation": "codex --skill mapbox-cartography \"<task>\""
    }
  ],
  "error_codes": {
    "1": "Skill invocation failed or required context was missing."
  },
  "tags": [
    "agent-skill",
    "devops",
    "mcpservers",
    "mit"
  ]
}
