{
  "name": "tech-debt-stryker-netx",
  "version": "0.1.0",
  "category": "devops",
  "description": "Identify, categorize, and prioritize technical debt.",
  "intent_triggers": [
    "use the tech debt agent skill",
    "run a workflow for tech debt",
    "help me with tech debt",
    "我需要處理 tech debt 相關工作",
    "幫我啟用 tech debt 這個 skill",
    "用 agent skill 完成 tech debt",
    "use tech debt from stryker-netx"
  ],
  "input_schema": {
    "task": {
      "type": "string",
      "required": true,
      "description": "Natural-language task or instruction for the agent skill."
    },
    "context_path": {
      "type": "string",
      "required": false,
      "description": "Optional workspace path or file context for the skill."
    }
  },
  "output_schema": {
    "format": "text",
    "fields": [
      "result",
      "notes"
    ]
  },
  "examples": [
    {
      "intent": "Use the tech debt skill for this task.",
      "invocation": "codex --skill tech-debt \"<task>\""
    }
  ],
  "error_codes": {
    "1": "Skill invocation failed or required context was missing."
  },
  "tags": [
    "agent-skill",
    "apache-2.0",
    "devops",
    "skills-rest"
  ]
}
