{
  "name": "dd-audit-cost-spike-investigation",
  "version": "0.1.0",
  "category": "ai-ml",
  "description": "Investigate a Datadog product usage or cost spike by correlating Usage Metering data (when/what spiked) with Audit Trail config changes (who changed what in the preceding window).",
  "intent_triggers": [
    "use the dd audit cost spike investigation agent skill",
    "run a workflow for dd audit cost spike investigation",
    "help me with dd audit cost spike investigation",
    "我需要處理 dd audit cost spike investigation 相關工作",
    "幫我啟用 dd audit cost spike investigation 這個 skill",
    "用 agent skill 完成 dd audit cost spike investigation"
  ],
  "input_schema": {
    "task": {
      "type": "string",
      "required": true,
      "description": "Natural-language task or instruction for the agent skill."
    },
    "context_path": {
      "type": "string",
      "required": false,
      "description": "Optional workspace path or file context for the skill."
    }
  },
  "output_schema": {
    "format": "text",
    "fields": [
      "result",
      "notes"
    ]
  },
  "examples": [
    {
      "intent": "Use the dd audit cost spike investigation skill for this task.",
      "invocation": "codex --skill dd-audit-cost-spike-investigation \"<task>\""
    }
  ],
  "error_codes": {
    "1": "Skill invocation failed or required context was missing."
  },
  "tags": [
    "agent-skill",
    "ai-ml",
    "mit",
    "skill"
  ]
}
