{
  "name": "neuroskill-bci",
  "version": "0.1.0",
  "category": "ai-ml",
  "description": "Agent skill for neuroskill bci workflows.",
  "intent_triggers": [
    "use the neuroskill bci agent skill",
    "run a workflow for neuroskill bci",
    "help me with neuroskill bci",
    "我需要處理 neuroskill bci 相關工作",
    "幫我啟用 neuroskill bci 這個 skill",
    "用 agent skill 完成 neuroskill bci",
    "use neuroskill bci from hermes-agent-zh"
  ],
  "input_schema": {
    "task": {
      "type": "string",
      "required": true,
      "description": "Natural-language task or instruction for the agent skill."
    },
    "context_path": {
      "type": "string",
      "required": false,
      "description": "Optional workspace path or file context for the skill."
    }
  },
  "output_schema": {
    "format": "text",
    "fields": [
      "result",
      "notes"
    ]
  },
  "examples": [
    {
      "intent": "Use the neuroskill bci skill for this task.",
      "invocation": "codex --skill neuroskill-bci \"<task>\""
    }
  ],
  "error_codes": {
    "1": "Skill invocation failed or required context was missing."
  },
  "tags": [
    "agent-skill",
    "ai-ml",
    "mit",
    "skills-rest"
  ]
}
